ycolor
