Metadata-Version: 1.0
Name: ycolor
Version: 1.1.1
Summary: A convenient color text printing tool
Home-page: UNKNOWN
Author: Yourourchour
Author-email: 348422509@qq.com
License: UNKNOWN
Platform: UNKNOWN
